analytics/__init__.py
analytics/src/__init__.py
analytics/src/cashflow.py
analytics/src/counterparty_info.py
analytics/src/date_utils.py
analytics/tests/__init__.py
analytics/tests/test_cashflow.py
analytics/tests/test_counterparty_info.py
analytics/tests/test_date_utils.py
smith_family_analytics-0.1.1.dist-info/METADATA
smith_family_analytics-0.1.1.dist-info/WHEEL
smith_family_analytics-0.1.1.dist-info/RECORD
